general_distribution/Binomialdistribution.py
general_distribution/Gaussiandistribution.py
general_distribution/Generaldistribution.py
general_distribution/__init__.py
general_distribution-0.0.1.dist-info/METADATA
general_distribution-0.0.1.dist-info/WHEEL
general_distribution-0.0.1.dist-info/top_level.txt
general_distribution-0.0.1.dist-info/RECORD
