Metadata-Version: 2.1
Name: general-distribution
Version: 0.0.1
Summary: probability distribution is the mathematical function that gives the probabilities of occurrence
Home-page: https://github.com/aquib1011/general-distribution
Author: Aquib Iqbal
License: MIT
Platform: UNKNOWN
Classifier: Programming Language :: Python :: 3
Classifier: License :: OSI Approved :: MIT License
Classifier: Operating System :: OS Independent
